happybase_mock/__init__.py
happybase_mock/batch.py
happybase_mock/connection.py
happybase_mock/pool.py
happybase_mock/table.py
happybase_mock-0.10.0.dist-info/METADATA
happybase_mock-0.10.0.dist-info/RECORD
happybase_mock-0.10.0.dist-info/WHEEL
happybase_mock-0.10.0.dist-info/top_level.txt
