Metadata-Version: 2.1
Name: happybase-mock
Version: 0.10.0
Summary: A mocking library for HappyBase
Home-page: https://github.com/eliangcs/happybase-mock
Author: Chang-Hung Liang
Author-email: eliang.cs@gmail.com
License: MIT
Platform: UNKNOWN
Classifier: Development Status :: 3 - Alpha
Classifier: Environment :: Console
Classifier: Intended Audience :: Developers
Classifier: License :: OSI Approved :: MIT License
Classifier: Operating System :: OS Independent
Classifier: Programming Language :: Python
Classifier: Programming Language :: Python :: 2.7
Classifier: Programming Language :: Python :: 3.6
Classifier: Topic :: Software Development :: Testing
